{
    "EKqkkYj-jhY": "GSTM1",
    "1Lq5UFRZ_zE": "GSTP1",
    "Et5wC2_U37Y": "GAMT",
    "jPhGnQqhrTE": "ADH1B",
    "ZCYSAhJYURs": "GGH",
    "fCsbe-HXcr4": "AGT",
    "PoMzEhWoceM": "NRG1",
    "bvdhopdC5GM": "NQO1",
    "jzenBdH-efs": "NAT2",
    "BFH6KRZS81Q": "NAT1",
    "dEhGR7dBzh0": "HTR2A",
    "5qhtoaQgBj8": "GSR",
    "tZdWO-SQcfc": "FUT2",
    "a1ZGOo35t24": "G6PD",
    "2MjP12uSbHw": "MAT2B",
    "mhldH-wrYfY": "MAT1A",
    "YSV7z-H-I9g": "IDO1",
    "fLK6nEloEY4": "MAT2A",
    "sd6UujGt7b8": "HRH1",
    "JLb4vMkW210": "HRH4",
    "DGC-P0e0xhw": "HNMT",
    "Xg_bNtL3izc": "HDC",
    "p8Nhy8N1jJ4": "MTHFR",
    "KKuAu-RY3VU": "DTNBP1",
    "BSmdOO5jCjY": "CAT",
    "sU1SO36EPR0": "GSS",
    "SUB1OPw9Jig": "HRH4",
    "I1oq4HXLJBw": "GPX3",
    "ErHtdZmn0i8": "GGT1",
    "wNAFN46RAfg": "APOC3",
    "parGjUuHAcI": "DMGDH",
    "knXWzqwgWSk": "DISC1",
    "jMnNHKP62eQ": "DHFR",
    "wUDYy96aums": "DAO",
    "BMnD8_rBLSU": "COMT",
    "Fe3X2yY5tfs": "AMT",
    "VZ4zys3rYz4": "ADK",
    "4uCU2ZrwDu0": "ADD1",
    "7MxmWQeEqMA": "ADA",
    "Rulupr4HrA4": "CYP2C9",
    "Huu5gwcU0m0": "ACE",
    "xK0C8Jd99BU": "ACAT1",
    "ROMlBdGf908": "CYP2D6",
    "xnUGxjQ3iyI": "CYP2C19",
    "mqYsF9_PpqA": "CYP2A6",
    "dCnRGmH0hxQ": "ABP1",
    "OjIqMkACEGY": "CYP4A11",
    "8ez_0J3AQDs": "BMP2",
    "91ugq1mPu-k": "CYP3A4",
    "p3JYJFHpMcg": "PON1",
    "ozi0K5pNHKw": "SOD3",
    "Yucm1mrp0qo": "CYP1B1",
    "7th_nXzQc2Y": "CYP2E1",
    "Uf_IW_Ahd6U": "CYP1A1",
    "JX91czj1oSg": "CYP1A2",
    "HNyuNrXtlmo": "AANAT"
}